skillforge/__init__.py
skillforge/__main__.py
skillforge/ai.py
skillforge/bundler.py
skillforge/cli.py
skillforge/scaffold.py
skillforge/skill.py
skillforge/validator.py
ai_skillforge-0.2.1.dist-info/METADATA
ai_skillforge-0.2.1.dist-info/WHEEL
ai_skillforge-0.2.1.dist-info/entry_points.txt
ai_skillforge-0.2.1.dist-info/licenses/LICENSE
ai_skillforge-0.2.1.dist-info/RECORD
