Metadata-Version: 2.4
Name: ai-skillforge
Version: 0.2.1
Summary: Create, validate, and bundle Anthropic Agent Skills — custom instructions that extend Claude's capabilities
Project-URL: Homepage, https://github.com/lhassa8/skillforge
Project-URL: Documentation, https://github.com/lhassa8/skillforge#readme
Project-URL: Repository, https://github.com/lhassa8/skillforge.git
Project-URL: Issues, https://github.com/lhassa8/skillforge/issues
Project-URL: Changelog, https://github.com/lhassa8/skillforge/blob/main/CHANGELOG.md
Author: SkillForge Contributors
Maintainer: SkillForge Contributors
License-Expression: MIT
License-File: LICENSE
Keywords: agent-skills,ai,anthropic,automation,claude,cli,llm,skills
Classifier: Development Status :: 4 - Beta
Classifier: Environment :: Console
Classifier: Intended Audience :: Developers
Classifier: License :: OSI Approved :: MIT License
Classifier: Operating System :: MacOS
Classifier: Operating System :: POSIX :: Linux
Classifier: Programming Language :: Python :: 3
Classifier: Programming Language :: Python :: 3.10
Classifier: Programming Language :: Python :: 3.11
Classifier: Programming Language :: Python :: 3.12
Classifier: Programming Language :: Python :: 3.13
Classifier: Topic :: Software Development :: Libraries :: Python Modules
Classifier: Topic :: Utilities
Classifier: Typing :: Typed
Requires-Python: >=3.10
Requires-Dist: pyyaml>=6.0
Requires-Dist: rich>=13.0.0
Requires-Dist: typer>=0.9.0
Provides-Extra: ai
Requires-Dist: anthropic>=0.18.0; extra == 'ai'
Requires-Dist: openai>=1.0.0; extra == 'ai'
Provides-Extra: anthropic
Requires-Dist: anthropic>=0.18.0; extra == 'anthropic'
Provides-Extra: dev
Requires-Dist: mypy>=1.0.0; extra == 'dev'
Requires-Dist: pytest-cov>=4.0.0; extra == 'dev'
Requires-Dist: pytest>=7.0.0; extra == 'dev'
Requires-Dist: ruff>=0.1.0; extra == 'dev'
Requires-Dist: types-pyyaml>=6.0.0; extra == 'dev'
Provides-Extra: openai
Requires-Dist: openai>=1.0.0; extra == 'openai'
